crimson/types/__init__.py
crimson/types/addon/__init__.py
crimson/types/addon/annotated.py
crimson/types/addon/intelli_type.py
crimson/types/addon/packs.py
crimson/types/addon/pydantic.py
crimson/types/control/number.py
crimson/types/torch/transformer/basic.py
crimson_types-0.1.6.dist-info/licenses/LICENSE
crimson_types-0.1.6.dist-info/METADATA
crimson_types-0.1.6.dist-info/WHEEL
crimson_types-0.1.6.dist-info/top_level.txt
crimson_types-0.1.6.dist-info/RECORD
